kelvin_sdk_datatype-8.0.3-py3.8-nspkg.pth
kelvin/sdk/datatype/__init__.py
kelvin/sdk/datatype/__main__.py
kelvin/sdk/datatype/base_messages.py
kelvin/sdk/datatype/datatype.py
kelvin/sdk/datatype/exception.py
kelvin/sdk/datatype/krn.py
kelvin/sdk/datatype/message.py
kelvin/sdk/datatype/model.py
kelvin/sdk/datatype/msg_builders.py
kelvin/sdk/datatype/msg_type.py
kelvin/sdk/datatype/package.py
kelvin/sdk/datatype/primitives.py
kelvin/sdk/datatype/py.typed
kelvin/sdk/datatype/types.py
kelvin/sdk/datatype/utils.py
kelvin/sdk/datatype/version.py
kelvin/sdk/datatype/cli/__init__.py
kelvin/sdk/datatype/cli/main.py
kelvin/sdk/datatype/cli/message.py
kelvin/sdk/datatype/vendor/__init__.py
kelvin/sdk/datatype/vendor/pyrobuf/__init__.py
kelvin/sdk/datatype/vendor/pyrobuf/parse_proto.py
kelvin_sdk_datatype-8.0.3.dist-info/LICENSE.rst
kelvin_sdk_datatype-8.0.3.dist-info/METADATA
kelvin_sdk_datatype-8.0.3.dist-info/WHEEL
kelvin_sdk_datatype-8.0.3.dist-info/entry_points.txt
kelvin_sdk_datatype-8.0.3.dist-info/namespace_packages.txt
kelvin_sdk_datatype-8.0.3.dist-info/top_level.txt
kelvin_sdk_datatype-8.0.3.dist-info/RECORD
